readme_coverage_badger/__init__.py
readme_coverage_badger/__main__.py
readme_coverage_badger-1.0.1.dist-info/AUTHORS.md
readme_coverage_badger-1.0.1.dist-info/LICENSE
readme_coverage_badger-1.0.1.dist-info/METADATA
readme_coverage_badger-1.0.1.dist-info/WHEEL
readme_coverage_badger-1.0.1.dist-info/entry_points.txt
readme_coverage_badger-1.0.1.dist-info/top_level.txt
readme_coverage_badger-1.0.1.dist-info/RECORD
