Metadata-Version: 2.1
Name: readme-coverage-badger
Version: 1.0.1
Summary: automatically generates your project's coverage badge using the shields.io service, and then updates your README
Home-page: https://github.com/engineervix/readme-coverage-badger/
Author: Victor Miti
Author-email: hello@victor.co.zm
License: BSD 3-Clause License
Project-URL: Bug Tracker, https://github.com/engineervix/readme-coverage-badger/issues
Project-URL: Changelog, https://github.com/engineervix/readme-coverage-badger/blob/master/CHANGELOG.md
Project-URL: Documentation, https://github.com/engineervix/readme-coverage-badger/blob/master/README.md
Project-URL: Download, https://pypi.org/project/readme-coverage-badger/#files
Project-URL: Source, https://github.com/engineervix/readme-coverage-badger/
Keywords: coverage badge shield readme
Platform: any
Classifier: Development Status :: 5 - Production/Stable
Classifier: Environment :: Console
Classifier: Intended Audience :: Developers
Classifier: License :: OSI Approved :: BSD License
Classifier: Natural Language :: English
Classifier: Operating System :: OS Independent
Classifier: Programming Language :: Python :: 3
Classifier: Programming Language :: Python :: 3 :: Only
Classifier: Programming Language :: Python :: 3.8
Classifier: Programming Language :: Python :: 3.9
Classifier: Programming Language :: Python :: 3.10
Classifier: Programming Language :: Python :: 3.11
Classifier: Programming Language :: Python :: 3.12
Classifier: Topic :: Software Development :: Testing
Classifier: Topic :: Text Processing :: Markup :: Markdown
Classifier: Topic :: Utilities
Requires-Python: >=3.8
License-File: LICENSE
License-File: AUTHORS.md
Requires-Dist: colorama
Requires-Dist: coverage
